data_validation_tool-0.1.0.dist-info/METADATA
data_validation_tool-0.1.0.dist-info/WHEEL
data_validation_tool-0.1.0.dist-info/entry_points.txt
data_validation_tool-0.1.0.dist-info/licenses/LICENSE
data_validation_tool/__init__.py
data_validation_tool/__main__.py
data_validation_tool/cli/__init__.py
data_validation_tool/cli/cloud.py
data_validation_tool/cli/init.py
data_validation_tool/cli/main.py
data_validation_tool/cli/run.py
data_validation_tool/core/__init__.py
data_validation_tool/core/exceptions.py
data_validation_tool/core/logger.py
data_validation_tool/core/models.py
data_validation_tool-0.1.0.dist-info/RECORD
