Metadata-Version: 2.1
Name: data-validation-tool
Version: 0.1.0
Summary: CLI tool for dbt data validation workflows
Keywords: dbt,data-validation,audit,cli
Author-Email: Infinite Lambda <dat@infinitelambda.com>
Classifier: Programming Language :: Python :: 3
Classifier: Programming Language :: Python :: 3.9
Classifier: Programming Language :: Python :: 3.10
Classifier: Programming Language :: Python :: 3.11
Classifier: Programming Language :: Python :: 3.12
Classifier: Programming Language :: Python :: 3.13
Classifier: License :: OSI Approved :: Apache Software License
Classifier: Operating System :: OS Independent
Classifier: Environment :: Console
Classifier: Intended Audience :: Developers
Classifier: Topic :: Database
Classifier: Topic :: Software Development :: Quality Assurance
Project-URL: Homepage, https://github.com/infinitelambda/data-validation-tool
Project-URL: Bug Tracker, https://github.com/infinitelambda/data-validation-tool/issues
Project-URL: Documentation, https://github.com/infinitelambda/data-validation-tool#readme
Requires-Python: >=3.9
Requires-Dist: click>=8.0.0
Requires-Dist: pyyaml>=6.0.0
Provides-Extra: dev
Requires-Dist: ruff>=0.8.0; extra == "dev"
Requires-Dist: pytest>=8.0.0; extra == "dev"
Requires-Dist: pytest-mock>=3.10.0; extra == "dev"
Requires-Dist: pytest-cov>=6.0.0; extra == "dev"
